intellex_shared_client/__init__.py
intellex_shared_client/api_client.py
intellex_shared_client/api_response.py
intellex_shared_client/configuration.py
intellex_shared_client/exceptions.py
intellex_shared_client/py.typed
intellex_shared_client/rest.py
intellex_shared_client/api/__init__.py
intellex_shared_client/api/auth_api.py
intellex_shared_client/api/default_api.py
intellex_shared_client/api/projects_api.py
intellex_shared_client/api/users_api.py
intellex_shared_client/models/__init__.py
intellex_shared_client/models/activity_item.py
intellex_shared_client/models/agent_thought.py
intellex_shared_client/models/api_key_payload.py
intellex_shared_client/models/api_key_summary.py
intellex_shared_client/models/api_keys_response.py
intellex_shared_client/models/chat_message.py
intellex_shared_client/models/create_message_request.py
intellex_shared_client/models/create_project_request.py
intellex_shared_client/models/delete_account_request.py
intellex_shared_client/models/device_delete_response.py
intellex_shared_client/models/device_list_response.py
intellex_shared_client/models/device_record.py
intellex_shared_client/models/device_revoke_request.py
intellex_shared_client/models/device_revoke_response.py
intellex_shared_client/models/device_upsert_request.py
intellex_shared_client/models/http_validation_error.py
intellex_shared_client/models/login_request.py
intellex_shared_client/models/preferences.py
intellex_shared_client/models/project_share.py
intellex_shared_client/models/project_stats.py
intellex_shared_client/models/research_plan.py
intellex_shared_client/models/research_plan_item.py
intellex_shared_client/models/research_project.py
intellex_shared_client/models/send_message_response.py
intellex_shared_client/models/share_project_request.py
intellex_shared_client/models/update_project_request.py
intellex_shared_client/models/user.py
intellex_shared_client/models/validation_error.py
intellex_shared_client/models/validation_error_loc_inner.py
intellex_shared_client-0.1.1.dist-info/METADATA
intellex_shared_client-0.1.1.dist-info/WHEEL
intellex_shared_client-0.1.1.dist-info/top_level.txt
intellex_shared_client-0.1.1.dist-info/RECORD
