Metadata-Version: 2.4
Name: intellex_shared_client
Version: 0.1.1
Summary: Intellex API Python client (generated from OpenAPI)
Home-page: 
Author: OpenAPI Generator community
Author-email: Intellex <team@intellex.ai>
Project-URL: Repository, https://github.com/intellex-ai/intellex-shared
Keywords: OpenAPI,Intellex API,client
Requires-Python: >=3.9
Requires-Dist: urllib3<3.0.0,>=2.1.0
Requires-Dist: python-dateutil>=2.8.2
Requires-Dist: pydantic>=2
Requires-Dist: typing-extensions>=4.7.1
Dynamic: author
